{
	"name": "redhpbackSmesh_",
	"plugin-id": "Sprite",
	"sid": 389106303832911,
	"isGlobal": false,
	"instanceVariables": [],
	"behaviorTypes": [],
	"effectTypes": [],
	"animations": {
		"items": [
			{
				"frames": [
					{
						"width": 250,
						"height": 250,
						"originX": 0,
						"originY": 0.5,
						"originalSource": "",
						"exportFormat": "lossless",
						"exportQuality": 0.8,
						"imageSpriteId": 5423999,
						"useCollisionPoly": true,
						"duration": 1
					}
				],
				"sid": 276988654701596,
				"name": "Animation 1",
				"isLooping": false,
				"isPingPong": false,
				"repeatCount": 1,
				"repeatTo": 0,
				"speed": 5
			}
		],
		"subfolders": []
	}
}