{
	"name": "Exit",
	"plugin-id": "Sprite",
	"sid": 986356030690106,
	"isGlobal": false,
	"instanceVariables": [],
	"behaviorTypes": [],
	"effectTypes": [],
	"animations": {
		"items": [
			{
				"frames": [
					{
						"width": 14,
						"height": 14,
						"originX": 0.5,
						"originY": 0.5,
						"originalSource": "",
						"exportFormat": "lossless",
						"exportQuality": 0.8,
						"imageSpriteId": 8744680,
						"collisionPoly": {
							"points": [
								0.1875,
								0.1875,
								0.5,
								0.03125,
								0.78125,
								0.1875,
								0.9375,
								0.5,
								0.8125,
								0.8125,
								0.5,
								0.9375,
								0.1875,
								0.78125,
								0.03125,
								0.5
							]
						},
						"useCollisionPoly": true,
						"duration": 1
					}
				],
				"sid": 614018272687076,
				"name": "Animation 1",
				"isLooping": false,
				"isPingPong": false,
				"repeatCount": 1,
				"repeatTo": 0,
				"speed": 5
			}
		],
		"subfolders": []
	}
}